probfindiff/__init__.py
probfindiff/_toplevel_api.py
probfindiff/_version.py
probfindiff/collocation.py
probfindiff/defaults.py
probfindiff/stencil.py
probfindiff/typing.py
probfindiff/utils/__init__.py
probfindiff/utils/autodiff.py
probfindiff/utils/kernel.py
probfindiff/utils/kernel_zoo.py
probfindiff-0.0.2.dist-info/LICENSE
probfindiff-0.0.2.dist-info/METADATA
probfindiff-0.0.2.dist-info/WHEEL
probfindiff-0.0.2.dist-info/top_level.txt
probfindiff-0.0.2.dist-info/RECORD
