Metadata-Version: 2.1
Name: probfindiff
Version: 0.0.2
Summary: Probabilistic numerical finite differences
Author: Nicholas Krämer
Author-email: nicholas.kraemer@uni-tuebingen.de
License: MIT
Requires-Python: >=3.8
License-File: LICENSE
Provides-Extra: ci
Requires-Dist: tox ; extra == 'ci'
Provides-Extra: cpu
Requires-Dist: jax[cpu] ; extra == 'cpu'
Provides-Extra: docs
Requires-Dist: jupyter ; extra == 'docs'
